python_sidekiq_client-0.9.4.dist-info/licenses/LICENSE
sidekiq_client/__init__.py
sidekiq_client/sidekiq_client.py
python_sidekiq_client-0.9.4.dist-info/METADATA
python_sidekiq_client-0.9.4.dist-info/WHEEL
python_sidekiq_client-0.9.4.dist-info/top_level.txt
python_sidekiq_client-0.9.4.dist-info/RECORD
